rdlexporter/__init__.py
rdlexporter/exporter.py
rdlexporter/py.typed
rdlexporter-0.4.0.dist-info/METADATA
rdlexporter-0.4.0.dist-info/WHEEL
rdlexporter-0.4.0.dist-info/RECORD
