Metadata-Version: 2.4
Name: rdlexporter
Version: 0.4.0
Summary: Library to export rdl files
Project-URL: Homepage, https://github.com/lowrisc/benevisrdl
Project-URL: Issues, https://github.com/lowrisc/benevisrdl/issues
Project-URL: Documentation, https://github.com/lowrisc/benevisrdl
Author: lowRISC contributors
Keywords: SystemRDL,exporter,library
Requires-Python: >=3.10
Requires-Dist: systemrdl-compiler~=1.32.1
